LICENSE
MANIFEST.in
README.md
requirements.txt
runtestserver.py
setup.py
xcessiv/__init__.py
xcessiv/automatedruns.py
xcessiv/config.py
xcessiv/constants.py
xcessiv/exceptions.py
xcessiv/functions.py
xcessiv/models.py
xcessiv/rqtasks.py
xcessiv/server.py
xcessiv/stacker.py
xcessiv/views.py
xcessiv.egg-info/PKG-INFO
xcessiv.egg-info/SOURCES.txt
xcessiv.egg-info/dependency_links.txt
xcessiv.egg-info/entry_points.txt
xcessiv.egg-info/requires.txt
xcessiv.egg-info/top_level.txt
xcessiv/presets/__init__.py
xcessiv/presets/cvsetting.py
xcessiv/presets/learnersetting.py
xcessiv/presets/learnersource.py
xcessiv/presets/metricsetting.py
xcessiv/presets/tests/__init__.py
xcessiv/presets/tests/test_cvsetting.py
xcessiv/presets/tests/test_learnersetting.py
xcessiv/presets/tests/test_metricsetting.py
xcessiv/scripts/__init__.py
xcessiv/scripts/runapp.py
xcessiv/scripts/runserver.py
xcessiv/scripts/runworker.py
xcessiv/tests/__init__.py
xcessiv/tests/extractmaindataset.py
xcessiv/tests/myrf.py
xcessiv/tests/test_functions.py
xcessiv/tests/test_models.py
xcessiv/tests/test_stacker.py
xcessiv/tests/test_views.py
xcessiv/ui/build/asset-manifest.json
xcessiv/ui/build/favicon.ico
xcessiv/ui/build/index.html
xcessiv/ui/build/static/css/main.ab674fca.css
xcessiv/ui/build/static/css/main.ab674fca.css.map
xcessiv/ui/build/static/js/main.bf33f9b8.js
xcessiv/ui/build/static/js/main.bf33f9b8.js.map
xcessiv/ui/build/static/media/glyphicons-halflings-regular.448c34a5.woff2
xcessiv/ui/build/static/media/glyphicons-halflings-regular.89889688.svg
xcessiv/ui/build/static/media/glyphicons-halflings-regular.e18bbf61.ttf
xcessiv/ui/build/static/media/glyphicons-halflings-regular.f4769f9b.eot
xcessiv/ui/build/static/media/glyphicons-halflings-regular.fa277232.woff