Metadata-Version: 1.1
Name: xcessiv
Version: 0.5.1
Summary: A web-based application for quick and scalable construction of massive machine learning ensembles.
Home-page: https://github.com/reiinakano/xcessiv
Author: Reiichiro Nakano
Author-email: reiichiro.s.nakano@gmail.com
License: Apache License 2.0
Platform: any
Classifier: Programming Language :: Python
Classifier: Programming Language :: Python :: 2
Classifier: Programming Language :: Python :: 2.7
Classifier: Programming Language :: Python :: 3
Classifier: Programming Language :: Python :: 3.5
Classifier: Programming Language :: JavaScript
Classifier: Natural Language :: English
Classifier: Intended Audience :: Developers
Classifier: Intended Audience :: Science/Research
Classifier: License :: OSI Approved :: Apache Software License
Classifier: Operating System :: Unix
Classifier: Topic :: Scientific/Engineering :: Artificial Intelligence
